CHANGES.txt
LICENSE.txt
MANIFEST.in
README.rst
contributors.txt
setup.py
geoshapespc/__init__.py
geoshapespc/cylinder.py
geoshapespc/geoshape.py
geoshapespc/noise.py
geoshapespc/point_inside_polygon.py
geoshapespc.egg-info/PKG-INFO
geoshapespc.egg-info/SOURCES.txt
geoshapespc.egg-info/dependency_links.txt
geoshapespc.egg-info/requires.txt
geoshapespc.egg-info/top_level.txt