Metadata-Version: 1.1
Name: geoshapespc
Version: 0.1.1
Summary: Generates a series of 3D point clouds around geometric shapes.
Home-page: https://bitbucket.org/matt_bv/geoshapespc
Author: Matheus Boni Vicari
Author-email: matheus.boni.vicari@gmail.com
License: LICENSE.txt
Keywords: geometric shapes point cloud LiDAR
Platform: UNKNOWN
Classifier: Programming Language :: Python
Classifier: Topic :: Scientific/Engineering
